{
  "code": "2003",
  "message": "成功",
  "resultId": 142,
  "resultIds": null,
  "relationResultId": null,
  "updateNumber": null,
  "result": null,
  "resultObject":
  {
    "id": 142,
    "remark": null,
    "designId": 42,
    "designRoomPartId": 409,
    "productId": 7475,
    "number": 5,
    "sortNo": "3",
    "product":
    {
      "goodsInfoId": 7475,
      "goodsId": 2732,
      "goodsInfoItemNo": "201809041402091",
      "goodsInfoBarcode": "",
      "goodsInfoName": "“逸·生活”-三人位沙发(灰绿)",
      "productName": null,
      "goodsName": null,
      "goodsInfoSubtitle": "",
      "subtitle": null,
      "goodsInfoAdded": "1",
      "goodsInfoAddedTime": null,
      "goodsInfoStock": 0,
      "goodsInfoPreferPrice": 3081.00,
      "goodsInfoCostPrice": 333.00,
      "goodsInfoMarketPrice": 5000.00,
      "goodsInfoWeight": 1.00,
      "goodsInfoImgId": "http://ruanzhuang-mall.oss-cn-hangzhou.aliyuncs.com/20180904/20180904140229ff8d819a0ef4417ebe596be645645b03.jpg@!thumbnail-rule-160",
      "goodsInfoDelflag": "0",
      "goodsSpecVo": null,
      "specView": "颜色:灰绿",
      "specRelList": [],
      "specVo": [
      {
        "releSpecDetailId": 6324,
        "goodsInfoId": 7475,
        "specValueRemark": "灰绿",
        "spec":
        {
          "specId": 579,
          "specName": "颜色",
          "specValue": null,
          "specRemark": "颜色（沙发）",
          "specNickname": "颜色（沙发）",
          "specShowtype": "0",
          "specShowmode": "1",
          "specDetails": [
          {
            "specDetailId": 2141,
            "specId": 579,
            "specDetailName": "浅棕",
            "specDetailNickname": null,
            "specDetailImg": null,
            "specDetailSort": 1,
            "specDetailDelflag": "0",
            "specDetailCreateName": "13724920715",
            "specDetailCreateTime": 1535678983000,
            "specDetailModifiedName": "admin",
            "specDetailModifiedTime": 1539847476000,
            "specDetailDelName": null,
            "specDetailDelTime": null
          },
          {
            "specDetailId": 2142,
            "specId": 579,
            "specDetailName": "灰蓝",
            "specDetailNickname": null,
            "specDetailImg": null,
            "specDetailSort": 2,
            "specDetailDelflag": "0",
            "specDetailCreateName": "13724920715",
            "specDetailCreateTime": 1535679012000,
            "specDetailModifiedName": "admin",
            "specDetailModifiedTime": 1539847476000,
            "specDetailDelName": null,
            "specDetailDelTime": null
          },
          {
            "specDetailId": 2143,
            "specId": 579,
            "specDetailName": "深蓝",
            "specDetailNickname": null,
            "specDetailImg": null,
            "specDetailSort": 3,
            "specDetailDelflag": "0",
            "specDetailCreateName": "13724920715",
            "specDetailCreateTime": 1535679012000,
            "specDetailModifiedName": "admin",
            "specDetailModifiedTime": 1539847476000,
            "specDetailDelName": null,
            "specDetailDelTime": null
          },
          {
            "specDetailId": 2144,
            "specId": 579,
            "specDetailName": "白色",
            "specDetailNickname": null,
            "specDetailImg": null,
            "specDetailSort": 4,
            "specDetailDelflag": "0",
            "specDetailCreateName": "13724920715",
            "specDetailCreateTime": 1535679012000,
            "specDetailModifiedName": "admin",
            "specDetailModifiedTime": 1539847476000,
            "specDetailDelName": null,
            "specDetailDelTime": null
          },
          {
            "specDetailId": 2146,
            "specId": 579,
            "specDetailName": "灰色",
            "specDetailNickname": null,
            "specDetailImg": null,
            "specDetailSort": 5,
            "specDetailDelflag": "0",
            "specDetailCreateName": "admin",
            "specDetailCreateTime": 1539847476000,
            "specDetailModifiedName": null,
            "specDetailModifiedTime": null,
            "specDetailDelName": null,
            "specDetailDelTime": null
          }]
        },
        "goodsSpecDetail":
        {
          "specDetailId": 2141,
          "specId": 579,
          "specDetailName": "浅棕",
          "specDetailNickname": null,
          "specDetailImg": null,
          "specDetailSort": 1,
          "specDetailDelflag": "0",
          "specDetailCreateName": "13724920715",
          "specDetailCreateTime": 1535678983000,
          "specDetailModifiedName": "admin",
          "specDetailModifiedTime": 1539847476000,
          "specDetailDelName": null,
          "specDetailDelTime": null
        }
      }],
      "openSpecVo": null,
      "goodsReleParamVos": null,
      "productWares": [
      {
        "id": 14682,
        "productId": 7475,
        "wareId": 86,
        "wareName": null,
        "wareStock": 11,
        "warePrice": 3081.00,
        "delFlag": "0"
      }],
      "goodsInfoCreateTime": null,
      "imageList": null,
      "thirdId": 0,
      "thirdName": "BOSS",
      "isThird": "0",
      "suitBuy": 0,
      "suitIds": null,
      "showList": "1",
      "showMobile": "1",
      "isCustomerDiscount": "0",
      "isMailBay": "0",
      "marketingId": null,
      "auditStatus": "3",
      "refuseReason": null,
      "suppList": null,
      "startTime": null,
      "endTime": null,
      "goodsCount": null,
      "isPresent": null,
      "catName": null,
      "brandName": null,
      "goods": null,
      "groupProductNum": null,
      "fictitiousSalesCount": null,
      "commentUtilBean": null,
      "catId": null,
      "thirdCatId": null,
      "brandId": null,
      "videoUrl": "",
      "videoType": "2",
      "salesCount": null,
      "erpCode": null
    }
  },
  "messageCode": "SUCCESS"
}
